workdown/__init__.py
workdown/workdown.py
workdown-0.0.4.dist-info/METADATA
workdown-0.0.4.dist-info/WHEEL
workdown-0.0.4.dist-info/entry_points.txt
workdown-0.0.4.dist-info/top_level.txt
workdown-0.0.4.dist-info/RECORD
