Metadata-Version: 2.1
Name: workdown
Version: 0.0.4
Summary: Write Markdown and have it published and hosted on Cloudflare Workers
Home-page: https://github.com/eldridgea/workdown
Author: Eldridge Alexander
Author-email: eldridgea@gmail.com
License: UNKNOWN
Platform: UNKNOWN
Classifier: Programming Language :: Python :: 3
Classifier: License :: OSI Approved :: MIT License
Classifier: Operating System :: OS Independent
Requires-Python: >=3.6
Requires-Dist: markdown
